[
  {
    "ts": "2025-08-14T22:30:30.961989+09:00",
    "id": "1955985386083164531",
    "text": "今日も無事完走！湯船でリセットしてね🛁 #水澄るう"
  },
  {
    "ts": "2025-08-14T22:53:09.784585+09:00",
    "id": "1955991085676650753",
    "text": "片付けまでが仕事、心までスッキリと。#水澄るう"
  },
  {
    "ts": "2025-08-15T08:33:12.743439+09:00",
    "id": "1956137059921650128",
    "text": "夏バテ注意！こまめに休憩・給水を。#水澄るう"
  },
  {
    "ts": "2025-08-15T19:44:39.435432+09:00",
    "id": "1956306034986746072",
    "text": "8月15日(金) 締めの一言：よく頑張った！ #水澄るう"
  },
  {
    "ts": "2025-08-16T08:33:15.663674+09:00",
    "id": "1956499459736588571",
    "text": "朝活スタート！安全第一・笑顔第一でいきましょう。#水澄るう"
  }
]